mapof/marriages/__init__.py
mapof/marriages/cultures_.py
mapof/marriages/distances_.py
mapof/marriages/features_.py
mapof/marriages/cultures/__init__.py
mapof/marriages/cultures/_utils.py
mapof/marriages/cultures/euclidean.py
mapof/marriages/cultures/impartial.py
mapof/marriages/cultures/mallows.py
mapof/marriages/cultures/urn.py
mapof/marriages/distances/__init__.py
mapof/marriages/distances/main_marriages_distances.py
mapof/marriages/features/__init__.py
mapof/marriages/features/basic_features.py
mapof/marriages/features/distance_to_stability_features.py
mapof/marriages/features/experiments_marriage.py
mapof/marriages/objects/Marriages.py
mapof/marriages/objects/MarriagesExperiment.py
mapof/marriages/objects/MarriagesFamily.py
mapof/marriages/objects/__init__.py
mapof/marriages/persistence/__init__.py
mapof/marriages/persistence/instance_exports.py
mapof/marriages/persistence/instance_imports.py
mapof_marriages-0.1.0b1.dist-info/LICENSE.txt
mapof_marriages-0.1.0b1.dist-info/METADATA
mapof_marriages-0.1.0b1.dist-info/WHEEL
mapof_marriages-0.1.0b1.dist-info/top_level.txt
mapof_marriages-0.1.0b1.dist-info/RECORD
