Metadata-Version: 2.1
Name: mapof-marriages
Version: 0.1.0b1
Summary: Map of Marriages
Author-email: Stanislaw Szufa <s.szufa@gmail.com>, Niclas Boehmer <niclas.boehmer@tu-berlin.de>
License: Copyright (c) 2018-2022 Stanislaw Szufa and contributors
Classifier: Programming Language :: Python :: 3
Classifier: License :: OSI Approved :: MIT License
Classifier: Operating System :: OS Independent
Requires-Python: >=3.10
License-File: LICENSE.txt
Requires-Dist: mapof==0.1.0b2
